Project_DataPrepKit/DataEncoding.py
Project_DataPrepKit/DataReading.py
Project_DataPrepKit/DataSummaries.py
Project_DataPrepKit/HandleMissingValues.py
Project_DataPrepKit/__init__.py
dataprepkit/DataEncoding.py
dataprepkit/DataReading.py
dataprepkit/DataSummaries.py
dataprepkit/HandleMissingValues.py
dataprepkit/__init__.py
Project_DataPrepKit-0.5.dist-info/METADATA
Project_DataPrepKit-0.5.dist-info/WHEEL
Project_DataPrepKit-0.5.dist-info/top_level.txt
Project_DataPrepKit-0.5.dist-info/RECORD
