Metadata-Version: 2.1
Name: Project-DataPrepKit
Version: 0.5
